README.rst
setup.py
django_smoknur/__init__.py
django_smoknur/middleware.py
django_smoknur/models.py
django_smoknur/tests.py
django_smoknur/urls.py
django_smoknur/views.py
django_smoknur.egg-info/PKG-INFO
django_smoknur.egg-info/SOURCES.txt
django_smoknur.egg-info/dependency_links.txt
django_smoknur.egg-info/not-zip-safe
django_smoknur.egg-info/top_level.txt
django_smoknur/management/__init__.py
django_smoknur/management/commands/__init__.py
django_smoknur/management/commands/load_dbg.py
django_smoknur/templates/debug.html