Metadata-Version: 1.0
Name: django-smoknur
Version: 0.3.13
Summary: UNKNOWN
Home-page: https://bitbucket.org/ilnurgi/django-smoknur
Author: Ilnur Gayfutdinov
Author-email: ilnurgi87@gmail.com
License: UNKNOWN
Platform: UNKNOWN
